selenium_youtube/__init__.py
selenium_youtube/youtube.py
selenium_youtube/enums/__init__.py
selenium_youtube/enums/analytics_period.py
selenium_youtube/enums/analytics_tab.py
selenium_youtube/enums/upload_status.py
selenium_youtube/enums/visibility.py
selenium_youtube-2.0.31.dist-info/LICENSE
selenium_youtube-2.0.31.dist-info/METADATA
selenium_youtube-2.0.31.dist-info/WHEEL
selenium_youtube-2.0.31.dist-info/top_level.txt
selenium_youtube-2.0.31.dist-info/RECORD
