Metadata-Version: 2.1
Name: selenium-youtube
Version: 2.0.31
Summary: selenium_youtube
Home-page: https://github.com/kkristof200/selenium_youtube
Author: Kovács Kristóf-Attila & Péntek Zsolt
Classifier: Programming Language :: Python :: 3.4
Classifier: Programming Language :: Python :: 3.5
Classifier: Programming Language :: Python :: 3.6
Classifier: Programming Language :: Python :: 3.7
Classifier: Programming Language :: Python :: 3.8
Classifier: Programming Language :: Python :: 3.9
Classifier: License :: OSI Approved :: MIT License
Classifier: Operating System :: OS Independent
Requires-Python: >=3.4
License-File: LICENSE
Requires-Dist: beautifulsoup4 (>=4.10.0)
Requires-Dist: kcu (>=0.0.73)
Requires-Dist: kstopit (>=0.0.16)
Requires-Dist: kyoutubescraper (>=0.0.2)
Requires-Dist: noraise (>=0.0.16)
Requires-Dist: selenium (>=4.0.0)
Requires-Dist: selenium-browser (>=0.0.12)
Requires-Dist: selenium-chrome (>=0.0.29)
Requires-Dist: selenium-firefox (>=2.0.8)
Requires-Dist: selenium-uploader-account (>=0.2.3)
Requires-Dist: setuptools (>=67.8.0)
Requires-Dist: xpath-utils (>=0.0.3)
